{
  "Rows": {
    "RowColumnAttachedInfos": {
      "2": {
        "GridRowColumnDefinition": {
          "DesignLengthInPixel": 25.0
        }
      },
      "3": {
        "GridRowColumnDefinition": {
          "DesignLengthInPixel": 25.0
        }
      },
      "4": {
        "GridRowColumnDefinition": {
          "DesignLengthInPixel": 25.0
        }
      },
      "5": {
        "GridRowColumnDefinition": {
          "DesignLengthInPixel": 25.0
        }
      },
      "6": {
        "GridRowColumnDefinition": {
          "DesignLengthInPixel": 25.0
        }
      },
      "7": {
        "GridRowColumnDefinition": {
          "DesignLengthInPixel": 25.0
        }
      },
      "8": {
        "GridRowColumnDefinition": {
          "DesignLengthInPixel": 25.0
        }
      },
      "9": {
        "GridRowColumnDefinition": {
          "DesignLengthInPixel": 25.0
        }
      },
      "12": {
        "GridRowColumnDefinition": {
          "DesignLengthInPixel": 25.0
        }
      },
      "14": {
        "GridRowColumnDefinition": {
          "DesignLengthInPixel": 25.0
        }
      },
      "15": {
        "GridRowColumnDefinition": {
          "DesignLengthInPixel": 25.0
        }
      },
      "16": {
        "GridRowColumnDefinition": {
          "DesignLengthInPixel": 30.0
        }
      },
      "17": {
        "GridRowColumnDefinition": {
          "DesignLengthInPixel": 20.0
        }
      },
      "19": {
        "GridRowColumnDefinition": {
          "DesignLengthInPixel": 25.0
        }
      },
      "20": {
        "GridRowColumnDefinition": {
          "DesignLengthInPixel": 25.0
        }
      },
      "21": {
        "GridRowColumnDefinition": {
          "DesignLengthInPixel": 25.0
        }
      },
      "30": {
        "GridRowColumnDefinition": {
          "DesignLengthInPixel": 20.0,
          "IsHidden": true
        }
      },
      "31": {
        "GridRowColumnDefinition": {
          "DesignLengthInPixel": 20.0,
          "IsHidden": true
        }
      }
    },
    "InLogicalVisibleIndexes": [
      23,
      24,
      25,
      26,
      27,
      28,
      29,
      30,
      31,
      32,
      33
    ],
    "Count": 34
  },
  "Cols": {
    "RowColumnAttachedInfos": {
      "1": {
        "GridRowColumnDefinition": {
          "DesignLengthInPixel": 20.0
        }
      },
      "3": {
        "GridRowColumnDefinition": {
          "DesignLengthInPixel": 20.0
        }
      },
      "4": {
        "GridRowColumnDefinition": {
          "DesignLengthInPixel": 20.0
        }
      },
      "5": {
        "GridRowColumnDefinition": {
          "DesignLengthInPixel": 20.0
        }
      },
      "6": {
        "GridRowColumnDefinition": {
          "DesignLengthInPixel": 20.0
        }
      },
      "7": {
        "GridRowColumnDefinition": {
          "DesignLengthInPixel": 20.0
        }
      },
      "8": {
        "GridRowColumnDefinition": {
          "DesignLengthInPixel": 20.0
        }
      },
      "9": {
        "GridRowColumnDefinition": {
          "DesignLengthInPixel": 20.0
        }
      },
      "10": {
        "GridRowColumnDefinition": {
          "DesignLengthInPixel": 20.0
        }
      },
      "11": {
        "GridRowColumnDefinition": {
          "DesignLengthInPixel": 20.0
        }
      },
      "12": {
        "GridRowColumnDefinition": {
          "DesignLengthInPixel": 20.0
        }
      },
      "13": {
        "GridRowColumnDefinition": {
          "DesignLengthInPixel": 20.0
        }
      },
      "14": {
        "GridRowColumnDefinition": {
          "DesignLengthInPixel": 20.0
        }
      },
      "15": {
        "GridRowColumnDefinition": {
          "DesignLengthInPixel": 20.0
        }
      },
      "16": {
        "GridRowColumnDefinition": {
          "DesignLengthInPixel": 20.0
        }
      },
      "17": {
        "GridRowColumnDefinition": {
          "DesignLengthInPixel": 20.0
        }
      },
      "18": {
        "GridRowColumnDefinition": {
          "DesignLengthInPixel": 20.0
        }
      },
      "19": {
        "GridRowColumnDefinition": {
          "DesignLengthInPixel": 10.0
        }
      },
      "20": {
        "GridRowColumnDefinition": {
          "DesignLengthInPixel": 10.0
        }
      },
      "21": {
        "GridRowColumnDefinition": {
          "DesignLengthInPixel": 20.0
        }
      },
      "22": {
        "GridRowColumnDefinition": {
          "DesignLengthInPixel": 20.0
        }
      },
      "23": {
        "GridRowColumnDefinition": {
          "DesignLengthInPixel": 20.0
        }
      },
      "24": {
        "GridRowColumnDefinition": {
          "DesignLengthInPixel": 20.0
        }
      },
      "25": {
        "GridRowColumnDefinition": {
          "DesignLengthInPixel": 10.0
        }
      },
      "26": {
        "GridRowColumnDefinition": {
          "DesignLengthInPixel": 10.0
        }
      },
      "27": {
        "GridRowColumnDefinition": {
          "DesignLengthInPixel": 20.0
        }
      },
      "28": {
        "GridRowColumnDefinition": {
          "DesignLengthInPixel": 20.0
        }
      },
      "29": {
        "GridRowColumnDefinition": {
          "DesignLengthInPixel": 20.0
        }
      },
      "30": {
        "GridRowColumnDefinition": {
          "DesignLengthInPixel": 20.0
        }
      },
      "31": {
        "GridRowColumnDefinition": {
          "DesignLengthInPixel": 20.0
        }
      }
    },
    "InLogicalVisibleIndexes": [
      34,
      35,
      36,
      37,
      38,
      39,
      40,
      41,
      42,
      43,
      44,
      45,
      46,
      47,
      48,
      49,
      50,
      51,
      52
    ],
    "Count": 53
  },
  "Values": {
    "0,35": "▼申込ID",
    "0,43": "▼更新フラグ",
    "3,35": "▼タスクID",
    "3,43": "▼編集許可フラグ",
    "4,43": 1,
    "6,35": "▼スケジュールメールID",
    "6,43": "▼元リマインド設定フラグ",
    "9,35": "▼タスク区分",
    "9,43": "▼元処理済みフラグ",
    "12,3": "期限日",
    "12,6": "＊",
    "12,18": "担当者",
    "12,22": "＊",
    "12,35": "▼ログインユーザーID",
    "12,43": "▼送信元区分",
    "13,35": "%CurrentUser.user_id%",
    "13,43": 1,
    "14,3": "※リマインドを設定すると期限日の当日に担当者に対してメール通知がされます",
    "15,35": "▼更新ユーザーID",
    "15,43": "▼取得宛先区分",
    "16,3": 0,
    "16,20": "ステータス",
    "16,24": 0,
    "18,35": "▼最終更新ラベル",
    "18,43": "▼取得差出人アドレス",
    "21,20": "削除する",
    "21,27": "登録する",
    "21,35": "▼メール本文取得フラグ",
    "21,43": "▼取得メールTO",
    "22,35": "0",
    "24,43": "▼取得メール件名",
    "27,43": "▼取得メール本文",
    "30,43": "▼取得完了フラグ",
    "31,43": "0"
  },
  "Formulas": {
    "19,3": "IF(AJ20<>\"\",\"最終更新日時：\"&AJ20,\"\")"
  },
  "AttachInfos": {
    "1,35": {
      "BindingInfo": {
        "TableName": "t_task",
        "ColumnName": "object_order_id"
      }
    },
    "2,3": {
      "CellType": {
        "$type": "Forguncy.MultilineTextBox, ServerDesignerCommon",
        "TemplateKey": "_RS_LightLine_Translucent_SmallRoundCorner_Normal1",
        "WaterMark": "タスク内容を入力してください"
      },
      "BindingInfo": {
        "TableName": "t_task",
        "ColumnName": "task_content"
      },
      "ConditionFormatRulesCollection": {
        "Rules": [
          {
            "$type": "Forguncy.ConditionFormat.FormulaRule, ServerDesignerCommon",
            "Formula": {
              "$type": "Forguncy.Model.FormulaReferObject, ServerDesignerCommon",
              "SerializeProperty": "=VALUE(タスク登録編集!編集許可フラグ)=0"
            },
            "StyleInfo": {
              "Underline": null,
              "Strikethrough": null
            },
            "IsDisabled": true,
            "IsInvisible": false,
            "IsReadOnly": false
          }
        ]
      }
    },
    "4,35": {
      "BindingInfo": {
        "TableName": "t_task",
        "ColumnName": "task_id"
      }
    },
    "4,43": {
      "CellType": {
        "$type": "Forguncy.TextCellType, ServerDesignerCommon",
        "SavedValidators": [
          {
            "$type": "Forguncy.CellTypes.Models.UniqueValidadator, ServerDesignerCommon"
          }
        ],
        "CellDefaultValue": 1
      },
      "CellComment": {
        "Comments": "画面の編集制御に使用"
      }
    },
    "7,35": {
      "BindingInfo": {
        "TableName": "t_task",
        "ColumnName": "schedule_mail_id"
      }
    },
    "7,43": {
      "BindingInfo": {
        "TableName": "t_task",
        "ColumnName": "remaind_flg"
      }
    },
    "10,35": {
      "BindingInfo": {
        "TableName": "t_task",
        "ColumnName": "task_type_id"
      }
    },
    "10,43": {
      "BindingInfo": {
        "TableName": "t_task",
        "ColumnName": "processed_flg"
      }
    },
    "12,8": {
      "CellType": {
        "$type": "Forguncy.DateCellType, ServerDesignerCommon",
        "TemplateKey": "_RS_LightLine_Translucent_SmallRoundCorner_Normal1"
      },
      "BindingInfo": {
        "TableName": "t_task",
        "ColumnName": "deadline"
      },
      "ConditionFormatRulesCollection": {
        "Rules": [
          {
            "$type": "Forguncy.ConditionFormat.FormulaRule, ServerDesignerCommon",
            "Formula": {
              "$type": "Forguncy.Model.FormulaReferObject, ServerDesignerCommon",
              "SerializeProperty": "=VALUE(タスク登録編集!編集許可フラグ)=0"
            },
            "StyleInfo": {
              "Underline": null,
              "Strikethrough": null
            },
            "IsDisabled": true,
            "IsInvisible": false,
            "IsReadOnly": false
          }
        ]
      }
    },
    "12,24": {
      "CellType": {
        "$type": "Forguncy.DropDownListCellType, ServerDesignerCommon",
        "MaxDropDownItemCount": 10,
        "TemplateKey": "_RS_LightLine_Translucent_SmallRoundCorner_Normal1",
        "IsBounding": true,
        "Items": [
          {
            "Value": "項目1",
            "DisplayValue": "項目1"
          },
          {
            "Value": "項目2",
            "DisplayValue": "項目2"
          },
          {
            "Value": "項目3",
            "DisplayValue": "項目3"
          }
        ],
        "DataSource": "m_user",
        "ValueColumnBindingInfo": {
          "TableName": "m_user",
          "ColumnName": "user_id"
        },
        "DisplayColumnBindingInfo": {
          "TableName": "m_user",
          "ColumnName": "user_name"
        },
        "ItemsQuery": {
          "$type": "ForguncyDataAccess.RelationSqlCondition, ForguncyDataAccess",
          "Condition1": {
            "$type": "ForguncyDataAccess.GeneralCESqlCondition, ForguncyDataAccess",
            "ColumnBindingInfo": {
              "TableName": "m_user",
              "ColumnName": "customer_id",
              "RelationBinding": {
                "RelatedTable": "m_customer",
                "RelatedColumn": "customer_id",
                "DisplayColumn": "main_office_flg"
              }
            },
            "Value": "1"
          },
          "Condition2": {
            "$type": "ForguncyDataAccess.GeneralCESqlCondition, ForguncyDataAccess",
            "ColumnBindingInfo": {
              "TableName": "m_user",
              "ColumnName": "active_flg"
            },
            "Value": "1"
          }
        },
        "CellDefaultValue": {
          "$type": "Forguncy.Model.FormulaReferObject, ServerDesignerCommon",
          "SerializeProperty": "=タスク登録編集!AJ14"
        }
      },
      "BindingInfo": {
        "TableName": "t_task",
        "ColumnName": "oparete_user_id"
      },
      "ConditionFormatRulesCollection": {
        "Rules": [
          {
            "$type": "Forguncy.ConditionFormat.FormulaRule, ServerDesignerCommon",
            "Formula": {
              "$type": "Forguncy.Model.FormulaReferObject, ServerDesignerCommon",
              "SerializeProperty": "=VALUE(タスク登録編集!編集許可フラグ)=0"
            },
            "StyleInfo": {
              "Underline": null,
              "Strikethrough": null
            },
            "IsDisabled": true,
            "IsInvisible": false,
            "IsReadOnly": false
          }
        ]
      }
    },
    "16,3": {
      "CellType": {
        "$type": "Forguncy.CheckBoxCellType, ServerDesignerCommon",
        "Caption": "リマインド設定する",
        "Style": 2,
        "PrimaryColor": "#FF005B47"
      },
      "BindingInfo": {
        "TableName": "t_task",
        "ColumnName": "remaind_flg"
      },
      "ConditionFormatRulesCollection": {
        "Rules": [
          {
            "$type": "Forguncy.ConditionFormat.FormulaRule, ServerDesignerCommon",
            "Formula": {
              "$type": "Forguncy.Model.FormulaReferObject, ServerDesignerCommon",
              "SerializeProperty": "=VALUE(タスク登録編集!編集許可フラグ)=0"
            },
            "StyleInfo": {
              "Underline": null,
              "Strikethrough": null
            },
            "IsDisabled": true,
            "IsInvisible": false,
            "IsReadOnly": false
          },
          {
            "$type": "Forguncy.ConditionFormat.CellValueRule, ServerDesignerCommon",
            "Operator": 3,
            "Value1": "=0",
            "StyleInfo": {
              "Foreground": "Text 1 50",
              "Underline": null,
              "Strikethrough": null
            }
          }
        ]
      }
    },
    "16,20": {
      "ConditionFormatRulesCollection": {
        "Rules": [
          {
            "$type": "Forguncy.ConditionFormat.FormulaRule, ServerDesignerCommon",
            "Formula": {
              "$type": "Forguncy.Model.FormulaReferObject, ServerDesignerCommon",
              "SerializeProperty": "=タスク登録編集!$AJ$5=\"\""
            },
            "StyleInfo": {
              "Underline": null,
              "Strikethrough": null
            },
            "IsDisabled": false,
            "IsInvisible": true,
            "IsReadOnly": false
          }
        ]
      }
    },
    "16,24": {
      "CellType": {
        "$type": "Forguncy.RadioGroupCellType, ServerDesignerCommon",
        "NoneItemText": "＜なし＞",
        "Style": 3,
        "PrimaryColor": "Accent 4 0",
        "CellDefaultValue": 0,
        "Items": [
          {
            "Value": "0",
            "DisplayValue": "未処理"
          },
          {
            "Value": "1",
            "DisplayValue": "処理済"
          }
        ]
      },
      "BindingInfo": {
        "TableName": "t_task",
        "ColumnName": "processed_flg"
      },
      "ConditionFormatRulesCollection": {
        "Rules": [
          {
            "$type": "Forguncy.ConditionFormat.FormulaRule, ServerDesignerCommon",
            "Formula": {
              "$type": "Forguncy.Model.FormulaReferObject, ServerDesignerCommon",
              "SerializeProperty": "=VALUE(タスク登録編集!編集許可フラグ)=0"
            },
            "StyleInfo": {
              "Underline": null,
              "Strikethrough": null
            },
            "IsDisabled": true,
            "IsInvisible": false,
            "IsReadOnly": false
          },
          {
            "$type": "Forguncy.ConditionFormat.FormulaRule, ServerDesignerCommon",
            "Formula": {
              "$type": "Forguncy.Model.FormulaReferObject, ServerDesignerCommon",
              "SerializeProperty": "=タスク登録編集!$AJ$5=\"\""
            },
            "StyleInfo": {
              "Underline": null,
              "Strikethrough": null
            },
            "IsDisabled": false,
            "IsInvisible": true,
            "IsReadOnly": false
          }
        ]
      }
    },
    "16,35": {
      "BindingInfo": {
        "TableName": "t_task",
        "ColumnName": "update_user_id"
      }
    },
    "19,35": {
      "BindingInfo": {
        "TableName": "t_task",
        "ColumnName": "last_updated_label"
      }
    },
    "21,20": {
      "CellType": {
        "$type": "Forguncy.ButtonCellType, ServerDesignerCommon",
        "CommandList": [
          {
            "$type": "Forguncy.Model.ConditionCommand, ServerDesignerCommon",
            "ConditionAndCommandPairList": [
              {
                "ConfirmDialogSettings": {
                  "Title": "確認",
                  "FormulaText": "この登録を削除します。よろしいですか？",
                  "YesButtonText": "はい",
                  "NoButtonText": "いいえ",
                  "ConfirmIcon": 4
                },
                "CommandList": [
                  {
                    "$type": "LoadingCommand.StartLoadingCommand, LoadingCommand",
                    "LoadingText": "お待ちください",
                    "LoadingTextColor": "Background 1 0"
                  },
                  {
                    "$type": "Forguncy.Model.RequestServerCommand, ServerDesignerCommon",
                    "ServerCommandName": "タスク削除処理",
                    "Parameters": [
                      {
                        "$type": "Forguncy.Model.RequestServerCommandObjectParam, ServerDesignerCommon",
                        "Value": {
                          "$type": "Forguncy.Model.FormulaReferObject, ServerDesignerCommon",
                          "SerializeProperty": "=タスク登録編集!AJ5"
                        },
                        "ParamName": "P_タスクID"
                      }
                    ],
                    "ResultErrorCodeTo": {
                      "SerializeProperty": "リターンコード"
                    },
                    "ResultMessageTo": {
                      "SerializeProperty": "リターンメッセージ"
                    },
                    "CheckDataValidation": false
                  },
                  {
                    "$type": "Forguncy.Model.ConditionCommand, ServerDesignerCommon",
                    "ConditionAndCommandPairList": [
                      {
                        "Condition": {
                          "$type": "Forguncy.Model.IfCondition, ServerDesignerCommon",
                          "param": {
                            "$type": "Forguncy.Model.IfConditionPageElementParam, ServerDesignerCommon",
                            "cellLocations": [
                              {
                                "SerializeProperty": "=タスク登録編集!リターンコード"
                              }
                            ]
                          },
                          "value": "0"
                        },
                        "CommandList": [
                          {
                            "$type": "Forguncy.Model.ClosePopupCommand, ServerDesignerCommon",
                            "ReloadData": true
                          }
                        ],
                        "ID": "d4ae1310-7e75-4b42-8d86-6313bd0300ba"
                      },
                      {
                        "CommandList": [
                          {
                            "$type": "Forguncy.Model.ShowMessageCommand, ServerDesignerCommon",
                            "MessageFormula": {
                              "$type": "Forguncy.Model.FormulaReferObject, ServerDesignerCommon",
                              "SerializeProperty": "=タスク登録編集!リターンメッセージ"
                            }
                          },
                          {
                            "$type": "LoadingCommand.EndLoadingCommand, LoadingCommand"
                          }
                        ],
                        "ID": "6b17b4b0-9016-412a-ace3-80016e401eb5"
                      }
                    ]
                  }
                ],
                "ID": "4df5ba51-3bc8-4a31-9c50-96b7f129a748"
              }
            ]
          }
        ],
        "Text": "削除する",
        "TemplateKey": "スタイル2"
      },
      "ConditionFormatRulesCollection": {
        "Rules": [
          {
            "$type": "Forguncy.ConditionFormat.FormulaRule, ServerDesignerCommon",
            "Formula": {
              "$type": "Forguncy.Model.FormulaReferObject, ServerDesignerCommon",
              "SerializeProperty": "=VALUE(タスク登録編集!編集許可フラグ)=0"
            },
            "StyleInfo": {
              "Underline": null,
              "Strikethrough": null
            },
            "IsDisabled": true,
            "IsInvisible": false,
            "IsReadOnly": false
          },
          {
            "$type": "Forguncy.ConditionFormat.FormulaRule, ServerDesignerCommon",
            "Formula": {
              "$type": "Forguncy.Model.FormulaReferObject, ServerDesignerCommon",
              "SerializeProperty": "=タスク登録編集!$AJ$5=\"\""
            },
            "StyleInfo": {
              "Underline": null,
              "Strikethrough": null
            },
            "IsDisabled": false,
            "IsInvisible": true,
            "IsReadOnly": false
          }
        ]
      }
    },
    "21,27": {
      "CellType": {
        "$type": "Forguncy.ButtonCellType, ServerDesignerCommon",
        "CommandList": [
          {
            "$type": "Forguncy.Model.ConditionCommand, ServerDesignerCommon",
            "ConditionAndCommandPairList": [
              {
                "Condition": {
                  "$type": "Forguncy.Model.IfCondition, ServerDesignerCommon",
                  "param": {
                    "$type": "Forguncy.Model.IfConditionPageElementParam, ServerDesignerCommon",
                    "cellLocations": [
                      {
                        "SerializeProperty": "=タスク登録編集!D3"
                      }
                    ]
                  },
                  "value": "%Null%"
                },
                "CommandList": [
                  {
                    "$type": "Forguncy.Model.ShowMessageCommand, ServerDesignerCommon",
                    "MessageFormula": "タスク内容を入力してください"
                  },
                  {
                    "$type": "SetFocusCommand.SetFocusCommand, SetFocusCommand",
                    "TargetCell": {
                      "$type": "Forguncy.Model.FormulaReferObject, ServerDesignerCommon",
                      "SerializeProperty": "=タスク登録編集!D3"
                    }
                  },
                  {
                    "$type": "Forguncy.Model.StopCommand, ServerDesignerCommon"
                  }
                ],
                "ID": "9680b3e4-34f3-4e2a-8914-35fe3c3ededa"
              }
            ]
          },
          {
            "$type": "Forguncy.Model.ConditionCommand, ServerDesignerCommon",
            "ConditionAndCommandPairList": [
              {
                "Condition": {
                  "$type": "ForguncyDataAccess.RelationSqlCondition, ForguncyDataAccess",
                  "Condition1": {
                    "$type": "Forguncy.Model.IfCondition, ServerDesignerCommon",
                    "param": {
                      "$type": "Forguncy.Model.IfConditionPageElementParam, ServerDesignerCommon",
                      "cellLocations": [
                        {
                          "SerializeProperty": "=タスク登録編集!D17"
                        }
                      ]
                    },
                    "value": "1"
                  },
                  "Condition2": {
                    "$type": "Forguncy.Model.IfCondition, ServerDesignerCommon",
                    "param": {
                      "$type": "Forguncy.Model.IfConditionPageElementParam, ServerDesignerCommon",
                      "cellLocations": [
                        {
                          "SerializeProperty": "=タスク登録編集!I13"
                        }
                      ]
                    },
                    "value": "%Null%"
                  }
                },
                "CommandList": [
                  {
                    "$type": "Forguncy.Model.ShowMessageCommand, ServerDesignerCommon",
                    "MessageFormula": "リマインドを設定する場合は、期限日を選択してください"
                  },
                  {
                    "$type": "SetFocusCommand.SetFocusCommand, SetFocusCommand",
                    "TargetCell": {
                      "$type": "Forguncy.Model.FormulaReferObject, ServerDesignerCommon",
                      "SerializeProperty": "=タスク登録編集!I13"
                    }
                  },
                  {
                    "$type": "Forguncy.Model.StopCommand, ServerDesignerCommon"
                  }
                ],
                "ID": "ad6cbb68-1abc-4ad8-b58c-595d1f274515"
              }
            ]
          },
          {
            "$type": "Forguncy.Model.ConditionCommand, ServerDesignerCommon",
            "ConditionAndCommandPairList": [
              {
                "Condition": {
                  "$type": "Forguncy.Model.IfCondition, ServerDesignerCommon",
                  "param": {
                    "$type": "Forguncy.Model.IfConditionPageElementParam, ServerDesignerCommon",
                    "cellLocations": [
                      {
                        "SerializeProperty": "=タスク登録編集!I13"
                      }
                    ]
                  },
                  "value": "%Null%"
                },
                "CommandList": [
                  {
                    "$type": "Forguncy.Model.ShowMessageCommand, ServerDesignerCommon",
                    "MessageFormula": "タスク期限日は必須となります"
                  },
                  {
                    "$type": "SetFocusCommand.SetFocusCommand, SetFocusCommand",
                    "TargetCell": {
                      "$type": "Forguncy.Model.FormulaReferObject, ServerDesignerCommon",
                      "SerializeProperty": "=タスク登録編集!I13"
                    }
                  },
                  {
                    "$type": "Forguncy.Model.StopCommand, ServerDesignerCommon"
                  }
                ],
                "ID": "43ab0cf2-b647-40de-9605-53a6bd6813bb"
              }
            ]
          },
          {
            "$type": "Forguncy.Model.ConditionCommand, ServerDesignerCommon",
            "ConditionAndCommandPairList": [
              {
                "Condition": {
                  "$type": "ForguncyDataAccess.RelationSqlCondition, ForguncyDataAccess",
                  "Condition1": {
                    "$type": "ForguncyDataAccess.RelationSqlCondition, ForguncyDataAccess",
                    "Condition1": {
                      "$type": "Forguncy.Model.IfCondition, ServerDesignerCommon",
                      "param": {
                        "$type": "Forguncy.Model.IfConditionPageElementParam, ServerDesignerCommon",
                        "cellLocations": [
                          {
                            "SerializeProperty": "=タスク登録編集!D17"
                          }
                        ]
                      },
                      "value": "True"
                    },
                    "Condition2": {
                      "$type": "Forguncy.Model.IfCondition, ServerDesignerCommon",
                      "param": {
                        "$type": "Forguncy.Model.IfConditionPageElementParam, ServerDesignerCommon",
                        "cellLocations": [
                          {
                            "SerializeProperty": "=タスク登録編集!Y17"
                          }
                        ]
                      },
                      "value": "0"
                    }
                  },
                  "Condition2": {
                    "$type": "Forguncy.Model.IfCondition, ServerDesignerCommon",
                    "param": {
                      "$type": "Forguncy.Model.IfConditionPageElementParam, ServerDesignerCommon",
                      "cellLocations": [
                        {
                          "SerializeProperty": "=タスク登録編集!AR8"
                        }
                      ]
                    },
                    "value": "1",
                    "compareType": 1
                  }
                },
                "CommandList": [
                  {
                    "$type": "Forguncy.Model.ConditionCommand, ServerDesignerCommon",
                    "ConditionAndCommandPairList": [
                      {
                        "ConfirmDialogSettings": {
                          "Title": "確認",
                          "FormulaText": "この投稿には、リマインドが設定されています。\r\n期限日当日にメール通知します。よろしいですか？",
                          "YesButtonText": "はい",
                          "NoButtonText": "いいえ",
                          "ConfirmIcon": 1
                        },
                        "CommandList": [
                          {
                            "$type": "Forguncy.Model.RunJavaScriptCommand, ServerDesignerCommon",
                            "JavaScript": "return true;",
                            "ID": "38d87688cb2747e1af3c86b5491f5790"
                          }
                        ],
                        "ID": "c5672e1c-71ec-4867-a1d5-fa064a2606af"
                      },
                      {
                        "CommandList": [
                          {
                            "$type": "Forguncy.Model.StopCommand, ServerDesignerCommon"
                          }
                        ],
                        "ID": "519b2c34-b2e2-4b35-a599-1f5b0cb2edfc"
                      }
                    ]
                  }
                ],
                "ID": "0e0c1ba7-a6de-4490-b568-57d5d02eafd4"
              }
            ]
          },
          {
            "$type": "Forguncy.Model.ConditionCommand, ServerDesignerCommon",
            "ConditionAndCommandPairList": [
              {
                "Condition": {
                  "$type": "ForguncyDataAccess.RelationSqlCondition, ForguncyDataAccess",
                  "Condition1": {
                    "$type": "Forguncy.Model.IfCondition, ServerDesignerCommon",
                    "param": {
                      "$type": "Forguncy.Model.IfConditionPageElementParam, ServerDesignerCommon",
                      "cellLocations": [
                        {
                          "SerializeProperty": "=タスク登録編集!Y17"
                        }
                      ]
                    },
                    "value": "1"
                  },
                  "Condition2": {
                    "$type": "Forguncy.Model.IfCondition, ServerDesignerCommon",
                    "param": {
                      "$type": "Forguncy.Model.IfConditionPageElementParam, ServerDesignerCommon",
                      "cellLocations": [
                        {
                          "SerializeProperty": "=タスク登録編集!AR11"
                        }
                      ]
                    },
                    "value": "0"
                  }
                },
                "CommandList": [
                  {
                    "$type": "Forguncy.Model.ShareCommand, ServerDesignerCommon",
                    "ShareCommandContainerRefer": {
                      "ShareCommandContainerID": "651037a9-ffaf-4591-9697-6b171676a452"
                    },
                    "Params": [
                      {
                        "ParamReferObject": {
                          "ParamID": "769b53af-30a0-4c8b-93cb-2097cb0976e4",
                          "ShareCommandContainerReferObject": {
                            "ShareCommandContainerID": "651037a9-ffaf-4591-9697-6b171676a452"
                          }
                        }
                      },
                      {
                        "ParamReferObject": {
                          "ParamID": "6c89412f-f509-4fef-b824-e7c2cb0fbece",
                          "ShareCommandContainerReferObject": {
                            "ShareCommandContainerID": "651037a9-ffaf-4591-9697-6b171676a452"
                          }
                        },
                        "Value": {
                          "$type": "Forguncy.Model.FormulaReferObject, ServerDesignerCommon",
                          "SerializeProperty": "=\"このタスクを処理済みに更新します\"&CHAR(10)&\"よろしいですか？\""
                        }
                      }
                    ],
                    "ReturnPropertiesTo": []
                  }
                ],
                "ID": "f5cae253-bd04-454e-81d9-41352606047b"
              },
              {
                "CommandList": [
                  {
                    "$type": "Forguncy.Model.ShareCommand, ServerDesignerCommon",
                    "ShareCommandContainerRefer": {
                      "ShareCommandContainerID": "651037a9-ffaf-4591-9697-6b171676a452"
                    },
                    "Params": [
                      {
                        "ParamReferObject": {
                          "ParamID": "769b53af-30a0-4c8b-93cb-2097cb0976e4",
                          "ShareCommandContainerReferObject": {
                            "ShareCommandContainerID": "651037a9-ffaf-4591-9697-6b171676a452"
                          }
                        },
                        "Value": {
                          "$type": "Forguncy.Model.FormulaReferObject, ServerDesignerCommon",
                          "SerializeProperty": "=タスク登録編集!AB22"
                        }
                      },
                      {
                        "ParamReferObject": {
                          "ParamID": "6c89412f-f509-4fef-b824-e7c2cb0fbece",
                          "ShareCommandContainerReferObject": {
                            "ShareCommandContainerID": "651037a9-ffaf-4591-9697-6b171676a452"
                          }
                        }
                      }
                    ],
                    "ReturnPropertiesTo": []
                  }
                ],
                "ID": "92dbe86e-02bd-4fa0-89e1-2461e38684a9"
              }
            ]
          },
          {
            "$type": "LoadingCommand.StartLoadingCommand, LoadingCommand",
            "LoadingText": "お待ちください",
            "LoadingTextColor": "Background 1 0"
          },
          {
            "$type": "Forguncy.Model.RequestServerCommand, ServerDesignerCommon",
            "ServerCommandName": "タスク登録処理",
            "Parameters": [
              {
                "$type": "Forguncy.Model.RequestServerCommandObjectParam, ServerDesignerCommon",
                "Value": {
                  "$type": "Forguncy.Model.FormulaReferObject, ServerDesignerCommon",
                  "SerializeProperty": "=タスク登録編集!AJ5"
                },
                "ParamName": "P_タスクID"
              },
              {
                "$type": "Forguncy.Model.RequestServerCommandObjectParam, ServerDesignerCommon",
                "Value": {
                  "$type": "Forguncy.Model.FormulaReferObject, ServerDesignerCommon",
                  "SerializeProperty": "=タスク登録編集!AJ2"
                },
                "ParamName": "P_申込ID"
              },
              {
                "$type": "Forguncy.Model.RequestServerCommandObjectParam, ServerDesignerCommon",
                "Value": {
                  "$type": "Forguncy.Model.FormulaReferObject, ServerDesignerCommon",
                  "SerializeProperty": "=IF(タスク登録編集!AJ11<>\"\",タスク登録編集!AJ11,3)"
                },
                "ParamName": "P_タスク区分"
              },
              {
                "$type": "Forguncy.Model.RequestServerCommandObjectParam, ServerDesignerCommon",
                "ParamName": "P_ユーザーグループID"
              },
              {
                "$type": "Forguncy.Model.RequestServerCommandObjectParam, ServerDesignerCommon",
                "Value": {
                  "$type": "Forguncy.Model.FormulaReferObject, ServerDesignerCommon",
                  "SerializeProperty": "=タスク登録編集!Y13"
                },
                "ParamName": "P_作業ユーザーID"
              },
              {
                "$type": "Forguncy.Model.RequestServerCommandObjectParam, ServerDesignerCommon",
                "Value": {
                  "$type": "Forguncy.Model.FormulaReferObject, ServerDesignerCommon",
                  "SerializeProperty": "=タスク登録編集!D3"
                },
                "ParamName": "P_タスク内容"
              },
              {
                "$type": "Forguncy.Model.RequestServerCommandObjectParam, ServerDesignerCommon",
                "Value": {
                  "$type": "Forguncy.Model.FormulaReferObject, ServerDesignerCommon",
                  "SerializeProperty": "=タスク登録編集!I13"
                },
                "ParamName": "P_期限日"
              },
              {
                "$type": "Forguncy.Model.RequestServerCommandObjectParam, ServerDesignerCommon",
                "Value": {
                  "$type": "Forguncy.Model.FormulaReferObject, ServerDesignerCommon",
                  "SerializeProperty": "=タスク登録編集!D17"
                },
                "ParamName": "P_リマインド設定フラグ"
              },
              {
                "$type": "Forguncy.Model.RequestServerCommandObjectParam, ServerDesignerCommon",
                "Value": {
                  "$type": "Forguncy.Model.FormulaReferObject, ServerDesignerCommon",
                  "SerializeProperty": "=タスク登録編集!Y17"
                },
                "ParamName": "P_処理済フラグ"
              }
            ],
            "ResultErrorCodeTo": {
              "SerializeProperty": "リターンコード"
            },
            "ResultMessageTo": {
              "SerializeProperty": "リターンメッセージ"
            },
            "ReturnPropertiesTo": [
              {
                "ResultPropertyName": "R_タスクID",
                "ResultTo": {
                  "SerializeProperty": "タスクID"
                }
              }
            ],
            "CheckDataValidation": false
          },
          {
            "$type": "Forguncy.Model.IgnorePageDirtyCommand, ServerDesignerCommon"
          },
          {
            "$type": "Forguncy.Model.ConditionCommand, ServerDesignerCommon",
            "ConditionAndCommandPairList": [
              {
                "Condition": {
                  "$type": "Forguncy.Model.IfCondition, ServerDesignerCommon",
                  "param": {
                    "$type": "Forguncy.Model.IfConditionPageElementParam, ServerDesignerCommon",
                    "cellLocations": [
                      {
                        "SerializeProperty": "=タスク登録編集!リターンコード"
                      }
                    ]
                  },
                  "value": "0"
                },
                "CommandList": [
                  {
                    "$type": "Forguncy.Model.SetCellPropertyCommand, ServerDesignerCommon",
                    "PropertyItemsList": [
                      {
                        "TargetCells": {
                          "$type": "Forguncy.Model.FormulaReferObject, ServerDesignerCommon",
                          "SerializeProperty": "=タスク登録編集!AJ5"
                        },
                        "Value": {
                          "$type": "Forguncy.Model.FormulaReferObject, ServerDesignerCommon",
                          "SerializeProperty": "=タスク登録編集!タスクID"
                        }
                      }
                    ]
                  },
                  {
                    "$type": "Forguncy.Model.SetCellPropertyCommand, ServerDesignerCommon",
                    "PropertyItemsList": [
                      {
                        "TargetCells": {
                          "$type": "Forguncy.Model.FormulaReferObject, ServerDesignerCommon",
                          "SerializeProperty": "=タスク登録編集!更新フラグ"
                        },
                        "Value": "1"
                      }
                    ],
                    "Comments": "更新フラグセット"
                  },
                  {
                    "$type": "Forguncy.Model.ConditionCommand, ServerDesignerCommon",
                    "ConditionAndCommandPairList": [
                      {
                        "Condition": {
                          "$type": "Forguncy.Model.IfCondition, ServerDesignerCommon",
                          "param": {
                            "$type": "Forguncy.Model.IfConditionPageElementParam, ServerDesignerCommon",
                            "cellLocations": [
                              {
                                "SerializeProperty": "=タスク登録編集!D17"
                              }
                            ]
                          },
                          "value": "True"
                        },
                        "CommandList": [
                          {
                            "$type": "Forguncy.Model.SetCellPropertyCommand, ServerDesignerCommon",
                            "PropertyItemsList": [
                              {
                                "TargetCells": {
                                  "$type": "Forguncy.Model.FormulaReferObject, ServerDesignerCommon",
                                  "SerializeProperty": "=タスク登録編集!AJ23"
                                },
                                "Value": "1"
                              }
                            ],
                            "Comments": "メール本文取得へ"
                          }
                        ],
                        "ID": "68f6cb70-0c38-430f-af04-2b772e1ccb94"
                      },
                      {
                        "CommandList": [
                          {
                            "$type": "Forguncy.Model.ClosePopupCommand, ServerDesignerCommon",
                            "PassValueBack": true,
                            "ReloadData": true
                          }
                        ],
                        "ID": "2d84b913-0845-4ae2-98f7-595007f8da68"
                      }
                    ]
                  }
                ],
                "ID": "a57bae82-2aa4-4050-ab5c-af841e26d85e"
              },
              {
                "CommandList": [
                  {
                    "$type": "Forguncy.Model.ShowMessageCommand, ServerDesignerCommon",
                    "MessageFormula": {
                      "$type": "Forguncy.Model.FormulaReferObject, ServerDesignerCommon",
                      "SerializeProperty": "=タスク登録編集!リターンメッセージ"
                    }
                  },
                  {
                    "$type": "LoadingCommand.EndLoadingCommand, LoadingCommand"
                  }
                ],
                "ID": "23fb705f-ae18-4939-bd10-c7dd3386b635"
              }
            ]
          }
        ],
        "Text": "登録する",
        "TemplateKey": "_RS_RoundCorner_Style1"
      },
      "ConditionFormatRulesCollection": {
        "Rules": [
          {
            "$type": "Forguncy.ConditionFormat.FormulaRule, ServerDesignerCommon",
            "Formula": {
              "$type": "Forguncy.Model.FormulaReferObject, ServerDesignerCommon",
              "SerializeProperty": "=VALUE(タスク登録編集!編集許可フラグ)=0"
            },
            "StyleInfo": {
              "Underline": null,
              "Strikethrough": null
            },
            "IsDisabled": true,
            "IsInvisible": false,
            "IsReadOnly": false
          }
        ]
      }
    },
    "22,35": {
      "CellType": {
        "$type": "Forguncy.TextCellType, ServerDesignerCommon",
        "SavedValidators": [
          {
            "$type": "Forguncy.CellTypes.Models.UniqueValidadator, ServerDesignerCommon"
          }
        ],
        "CommandList": [
          {
            "$type": "Forguncy.Model.SetCellPropertyCommand, ServerDesignerCommon",
            "PropertyItemsList": [
              {
                "TargetCells": {
                  "$type": "Forguncy.Model.FormulaReferObject, ServerDesignerCommon",
                  "SerializeProperty": "=タスク登録編集!AJ23"
                },
                "Value": "0"
              }
            ]
          },
          {
            "$type": "Forguncy.Model.Commands.SetParameterCommand, ServerDesignerCommon",
            "ParameterName": "テンプレートID",
            "TableValue": {
              "TableName": "m_mail_template",
              "OnlyGetValue": true,
              "TableValueType": 0,
              "BindingInfos": [
                {
                  "BindingInfo": {
                    "TableName": "m_mail_template",
                    "ColumnName": "template_id"
                  },
                  "ColumnName": "template_id"
                }
              ],
              "SqlCondition": {
                "$type": "ForguncyDataAccess.GeneralCESqlCondition, ForguncyDataAccess",
                "ColumnBindingInfo": {
                  "TableName": "m_mail_template",
                  "ColumnName": "system_button_name"
                },
                "Value": "タスクリマインド通知ボタン"
              }
            },
            "ID": "da1fbb8c211142899f2b6386e6e76d21"
          },
          {
            "$type": "Forguncy.Model.ShowPopupCommand, ServerDesignerCommon",
            "PageName": "メール送信ポップアップ",
            "PassValues": [
              {
                "Source": "1",
                "TargetCell": {
                  "SerializeProperty": "=メール送信ポップアップ!メール本文取得フラグ"
                }
              },
              {
                "Source": {
                  "$type": "Forguncy.Model.FormulaReferObject, ServerDesignerCommon",
                  "SerializeProperty": "=タスク登録編集!テンプレートID"
                },
                "TargetCell": {
                  "SerializeProperty": "=メール送信ポップアップ!テンプレートID"
                }
              },
              {
                "Source": {
                  "$type": "Forguncy.Model.FormulaReferObject, ServerDesignerCommon",
                  "SerializeProperty": "=タスク登録編集!Y13"
                },
                "TargetCell": {
                  "SerializeProperty": "=メール送信ポップアップ!指定ユーザーID"
                }
              },
              {
                "Source": {
                  "$type": "Forguncy.Model.FormulaReferObject, ServerDesignerCommon",
                  "SerializeProperty": "=タスク登録編集!AJ5"
                },
                "TargetCell": {
                  "SerializeProperty": "=メール送信ポップアップ!タスクID"
                }
              },
              {
                "Source": {
                  "$type": "Forguncy.Model.FormulaReferObject, ServerDesignerCommon",
                  "SerializeProperty": "=タスク登録編集!AR20"
                },
                "TargetCell": {
                  "SerializeProperty": "=メール送信ポップアップ!返却差出人アドレス"
                }
              },
              {
                "Source": {
                  "$type": "Forguncy.Model.FormulaReferObject, ServerDesignerCommon",
                  "SerializeProperty": "=タスク登録編集!AR17"
                },
                "TargetCell": {
                  "SerializeProperty": "=メール送信ポップアップ!返却宛先区分"
                }
              },
              {
                "Source": {
                  "$type": "Forguncy.Model.FormulaReferObject, ServerDesignerCommon",
                  "SerializeProperty": "=タスク登録編集!AR23"
                },
                "TargetCell": {
                  "SerializeProperty": "=メール送信ポップアップ!返却メールTO"
                }
              },
              {
                "Source": {
                  "$type": "Forguncy.Model.FormulaReferObject, ServerDesignerCommon",
                  "SerializeProperty": "=タスク登録編集!AR26"
                },
                "TargetCell": {
                  "SerializeProperty": "=メール送信ポップアップ!返却メール件名"
                }
              },
              {
                "Source": {
                  "$type": "Forguncy.Model.FormulaReferObject, ServerDesignerCommon",
                  "SerializeProperty": "=タスク登録編集!AR29"
                },
                "TargetCell": {
                  "SerializeProperty": "=メール送信ポップアップ!返却メール本文"
                }
              },
              {
                "Source": {
                  "$type": "Forguncy.Model.FormulaReferObject, ServerDesignerCommon",
                  "SerializeProperty": "=タスク登録編集!AR32"
                },
                "TargetCell": {
                  "SerializeProperty": "=メール送信ポップアップ!取得完了フラグ"
                }
              }
            ]
          }
        ],
        "CellDefaultValue": "0"
      }
    },
    "31,43": {
      "CellType": {
        "$type": "Forguncy.TextCellType, ServerDesignerCommon",
        "SavedValidators": [
          {
            "$type": "Forguncy.CellTypes.Models.UniqueValidadator, ServerDesignerCommon"
          }
        ],
        "CommandList": [
          {
            "$type": "Forguncy.Model.ConditionCommand, ServerDesignerCommon",
            "ConditionAndCommandPairList": [
              {
                "Condition": {
                  "$type": "Forguncy.Model.IfCondition, ServerDesignerCommon",
                  "param": {
                    "$type": "Forguncy.Model.IfConditionPageElementParam, ServerDesignerCommon",
                    "cellLocations": [
                      {
                        "SerializeProperty": "=タスク登録編集!AR32"
                      }
                    ]
                  },
                  "value": "1"
                },
                "CommandList": [
                  {
                    "$type": "Forguncy.Model.SetCellPropertyCommand, ServerDesignerCommon",
                    "PropertyItemsList": [
                      {
                        "TargetCells": {
                          "$type": "Forguncy.Model.FormulaReferObject, ServerDesignerCommon",
                          "SerializeProperty": "=タスク登録編集!AR32"
                        },
                        "Value": "0"
                      }
                    ],
                    "Comments": "フラグリセット"
                  },
                  {
                    "$type": "Forguncy.Model.RequestServerCommand, ServerDesignerCommon",
                    "ServerCommandName": "スケジュールメール登録",
                    "Parameters": [
                      {
                        "$type": "Forguncy.Model.RequestServerCommandObjectParam, ServerDesignerCommon",
                        "Value": {
                          "$type": "Forguncy.Model.FormulaReferObject, ServerDesignerCommon",
                          "SerializeProperty": "=タスク登録編集!AJ8"
                        },
                        "ParamName": "P_スケジュールメールID"
                      },
                      {
                        "$type": "Forguncy.Model.RequestServerCommandObjectParam, ServerDesignerCommon",
                        "Value": {
                          "$type": "Forguncy.Model.FormulaReferObject, ServerDesignerCommon",
                          "SerializeProperty": "=タスク登録編集!AJ2"
                        },
                        "ParamName": "P_申込ID"
                      },
                      {
                        "$type": "Forguncy.Model.RequestServerCommandObjectParam, ServerDesignerCommon",
                        "Value": {
                          "$type": "Forguncy.Model.FormulaReferObject, ServerDesignerCommon",
                          "SerializeProperty": "=タスク登録編集!AR14"
                        },
                        "ParamName": "P_送信元区分"
                      },
                      {
                        "$type": "Forguncy.Model.RequestServerCommandObjectParam, ServerDesignerCommon",
                        "Value": {
                          "$type": "Forguncy.Model.FormulaReferObject, ServerDesignerCommon",
                          "SerializeProperty": "=タスク登録編集!AR17"
                        },
                        "ParamName": "P_宛先区分"
                      },
                      {
                        "$type": "Forguncy.Model.RequestServerCommandObjectParam, ServerDesignerCommon",
                        "Value": {
                          "$type": "Forguncy.Model.FormulaReferObject, ServerDesignerCommon",
                          "SerializeProperty": "=タスク登録編集!AR20"
                        },
                        "ParamName": "P_差出人アドレス"
                      },
                      {
                        "$type": "Forguncy.Model.RequestServerCommandObjectParam, ServerDesignerCommon",
                        "ParamName": "P_ユーザーグループID"
                      },
                      {
                        "$type": "Forguncy.Model.RequestServerCommandObjectParam, ServerDesignerCommon",
                        "Value": {
                          "$type": "Forguncy.Model.FormulaReferObject, ServerDesignerCommon",
                          "SerializeProperty": "=タスク登録編集!AR23"
                        },
                        "ParamName": "P_宛先TO"
                      },
                      {
                        "$type": "Forguncy.Model.RequestServerCommandObjectParam, ServerDesignerCommon",
                        "ParamName": "P_宛先CC"
                      },
                      {
                        "$type": "Forguncy.Model.RequestServerCommandObjectParam, ServerDesignerCommon",
                        "Value": {
                          "$type": "Forguncy.Model.FormulaReferObject, ServerDesignerCommon",
                          "SerializeProperty": "=タスク登録編集!AR26"
                        },
                        "ParamName": "P_件名"
                      },
                      {
                        "$type": "Forguncy.Model.RequestServerCommandObjectParam, ServerDesignerCommon",
                        "Value": {
                          "$type": "Forguncy.Model.FormulaReferObject, ServerDesignerCommon",
                          "SerializeProperty": "=タスク登録編集!AR29"
                        },
                        "ParamName": "P_本文"
                      },
                      {
                        "$type": "Forguncy.Model.RequestServerCommandObjectParam, ServerDesignerCommon",
                        "Value": {
                          "$type": "Forguncy.Model.FormulaReferObject, ServerDesignerCommon",
                          "SerializeProperty": "=タスク登録編集!AJ5"
                        },
                        "ParamName": "P_タスクID"
                      },
                      {
                        "$type": "Forguncy.Model.RequestServerCommandObjectParam, ServerDesignerCommon",
                        "Value": {
                          "$type": "Forguncy.Model.FormulaReferObject, ServerDesignerCommon",
                          "SerializeProperty": "=タスク登録編集!I13"
                        },
                        "ParamName": "P_送信予定日"
                      }
                    ],
                    "ResultErrorCodeTo": {
                      "SerializeProperty": "リターンコード"
                    },
                    "ResultMessageTo": {
                      "SerializeProperty": "リターンメッセージ"
                    },
                    "CheckDataValidation": false
                  },
                  {
                    "$type": "Forguncy.Model.ConditionCommand, ServerDesignerCommon",
                    "ConditionAndCommandPairList": [
                      {
                        "Condition": {
                          "$type": "Forguncy.Model.IfCondition, ServerDesignerCommon",
                          "param": {
                            "$type": "Forguncy.Model.IfConditionPageElementParam, ServerDesignerCommon",
                            "cellLocations": [
                              {
                                "SerializeProperty": "=タスク登録編集!リターンコード"
                              }
                            ]
                          },
                          "value": "0"
                        },
                        "CommandList": [
                          {
                            "$type": "Forguncy.Model.ClosePopupCommand, ServerDesignerCommon",
                            "PassValueBack": true,
                            "ReloadData": true
                          }
                        ],
                        "ID": "0d96e2e9-81f7-41e0-99ab-3d10a81f9ed7"
                      },
                      {
                        "CommandList": [
                          {
                            "$type": "Forguncy.Model.ShowMessageCommand, ServerDesignerCommon",
                            "MessageFormula": {
                              "$type": "Forguncy.Model.FormulaReferObject, ServerDesignerCommon",
                              "SerializeProperty": "=タスク登録編集!リターンメッセージ"
                            }
                          }
                        ],
                        "ID": "14221d7d-1b7d-4172-b1c5-3ef8429b549a"
                      }
                    ]
                  }
                ],
                "ID": "8bbac96c-0853-433f-b646-3c9f84c61f0c"
              }
            ]
          }
        ],
        "CellDefaultValue": "0"
      }
    }
  },
  "StyleDatas": {
    "Styles": [
      {
        "BorderLeft": 0
      },
      {
        "FontFamily": 1,
        "Formatter": 2
      },
      {
        "FontFamily": 1
      },
      {
        "Background": 3,
        "FontFamily": 1
      },
      {
        "Background": 4
      },
      {
        "Formatter": 5,
        "VerticalAlignment": 6,
        "WordWrap": true
      },
      {
        "FontFamily": 1,
        "Formatter": 5,
        "VerticalAlignment": 6,
        "WordWrap": true
      },
      {
        "Background": 3,
        "FontFamily": 1,
        "Formatter": 5,
        "VerticalAlignment": 6,
        "WordWrap": true
      },
      {
        "Background": 3,
        "FontFamily": 1,
        "Formatter": 5,
        "HorizontalAlignment": 7
      },
      {
        "Background": 3
      },
      {
        "FontFamily": 1,
        "Foreground": 8
      },
      {
        "FontFamily": 1,
        "FontSize": 14.666666666666666
      },
      {
        "Background": 9,
        "FontFamily": 1,
        "Formatter": 2
      },
      {
        "Foreground": 10
      },
      {
        "FontFamily": 1,
        "FontSize": 12.0,
        "HorizontalAlignment": 11
      },
      {
        "FontFamily": 1,
        "FontSize": 12.0,
        "Foreground": 12,
        "Formatter": 13,
        "TextIndent": 4,
        "ShrinkToFit": true
      },
      {
        "FontFamily": 1,
        "FontSize": 12.0
      },
      {
        "Background": 14,
        "FontFamily": 1,
        "Foreground": 15,
        "Formatter": 5,
        "HorizontalAlignment": 7
      },
      {
        "Background": 14,
        "FontFamily": 1,
        "Formatter": 5,
        "HorizontalAlignment": 7
      }
    ],
    "Types": {
      "Strs": [
        "Background 1 -15",
        "Body",
        "[AUTO]General",
        "#FFFFFF00",
        "#FFFFC000",
        "@",
        "Top",
        "Right",
        "#FF92D050",
        "Accent 6 80",
        "#FFC00000",
        "Center",
        "Text 1 50",
        "yyyy/mm/dd hh:mm",
        "Accent 1 60",
        "#FF000000"
      ],
      "Borders": [
        {
          "Color": 0
        }
      ]
    },
    "CellStyles": {
      "0,0": 0,
      "0,35": 1,
      "0,36": 2,
      "0,37": 2,
      "0,38": 2,
      "0,39": 2,
      "0,40": 2,
      "0,41": 2,
      "1,0": 0,
      "1,35": 3,
      "1,36": 2,
      "1,37": 2,
      "1,38": 2,
      "1,39": 2,
      "1,40": 2,
      "1,41": 2,
      "1,43": 4,
      "2,0": 0,
      "2,3": 5,
      "2,32": 5,
      "2,33": 5,
      "2,35": 6,
      "2,36": 6,
      "2,37": 6,
      "2,38": 5,
      "2,39": 5,
      "2,40": 5,
      "2,41": 5,
      "2,42": 2,
      "2,43": 2,
      "2,44": 2,
      "2,45": 5,
      "2,46": 5,
      "2,47": 5,
      "3,0": 0,
      "3,32": 5,
      "3,33": 5,
      "3,35": 1,
      "3,36": 6,
      "3,37": 6,
      "3,38": 5,
      "3,39": 5,
      "3,40": 5,
      "3,41": 5,
      "3,43": 1,
      "3,44": 2,
      "3,45": 2,
      "3,46": 5,
      "3,47": 5,
      "4,0": 0,
      "4,32": 5,
      "4,33": 5,
      "4,35": 7,
      "4,38": 5,
      "4,39": 5,
      "4,40": 5,
      "4,41": 5,
      "4,43": 8,
      "4,44": 2,
      "4,45": 2,
      "4,46": 5,
      "4,47": 5,
      "5,0": 0,
      "5,32": 5,
      "5,33": 5,
      "5,35": 2,
      "5,36": 2,
      "5,37": 2,
      "5,38": 5,
      "5,39": 5,
      "5,40": 5,
      "5,41": 5,
      "5,42": 2,
      "5,43": 2,
      "5,44": 2,
      "5,45": 5,
      "5,46": 5,
      "5,47": 5,
      "5,48": 5,
      "5,52": 5,
      "6,0": 0,
      "6,32": 5,
      "6,33": 5,
      "6,35": 1,
      "6,36": 6,
      "6,37": 6,
      "6,39": 5,
      "6,40": 5,
      "6,41": 5,
      "6,43": 1,
      "6,44": 2,
      "6,45": 2,
      "6,46": 5,
      "6,47": 5,
      "6,48": 5,
      "6,52": 5,
      "7,0": 0,
      "7,32": 5,
      "7,33": 5,
      "7,35": 7,
      "7,39": 5,
      "7,40": 5,
      "7,41": 5,
      "7,43": 3,
      "7,46": 5,
      "7,47": 5,
      "7,48": 5,
      "7,52": 5,
      "8,0": 0,
      "8,32": 5,
      "8,33": 5,
      "8,37": 5,
      "8,38": 5,
      "8,39": 5,
      "8,40": 5,
      "8,41": 5,
      "8,42": 2,
      "8,43": 2,
      "8,44": 2,
      "8,45": 5,
      "8,46": 5,
      "8,47": 5,
      "8,48": 5,
      "8,52": 5,
      "9,0": 0,
      "9,32": 5,
      "9,33": 5,
      "9,38": 5,
      "9,39": 5,
      "9,40": 5,
      "9,41": 5,
      "9,43": 1,
      "9,45": 5,
      "9,46": 5,
      "9,47": 5,
      "9,48": 5,
      "9,52": 5,
      "10,0": 0,
      "10,35": 9,
      "10,43": 3,
      "11,0": 0,
      "12,0": 0,
      "12,6": 10,
      "12,8": 11,
      "12,9": 2,
      "12,10": 2,
      "12,11": 2,
      "12,12": 2,
      "12,13": 2,
      "12,18": 2,
      "12,20": 1,
      "12,22": 10,
      "12,35": 1,
      "12,36": 2,
      "12,37": 2,
      "12,43": 1,
      "12,44": 2,
      "12,45": 2,
      "13,0": 0,
      "13,35": 3,
      "13,36": 2,
      "13,37": 2,
      "13,43": 12,
      "13,44": 2,
      "13,45": 2,
      "14,0": 0,
      "14,3": 13,
      "14,46": 2,
      "14,47": 2,
      "14,48": 2,
      "14,52": 2,
      "15,0": 0,
      "15,43": 1,
      "15,44": 2,
      "15,45": 2,
      "15,46": 2,
      "15,47": 2,
      "15,48": 2,
      "16,0": 0,
      "16,3": 2,
      "16,20": 2,
      "16,24": 14,
      "16,35": 9,
      "16,42": 2,
      "16,43": 3,
      "16,44": 2,
      "16,45": 2,
      "16,46": 2,
      "16,47": 2,
      "16,48": 2,
      "17,0": 0,
      "17,43": 2,
      "17,44": 2,
      "17,45": 2,
      "17,46": 2,
      "17,47": 2,
      "17,48": 2,
      "18,0": 0,
      "18,35": 2,
      "18,36": 2,
      "18,37": 2,
      "18,43": 1,
      "18,44": 2,
      "18,45": 2,
      "18,46": 2,
      "18,47": 2,
      "18,48": 2,
      "19,0": 0,
      "19,3": 15,
      "19,35": 3,
      "19,36": 2,
      "19,37": 2,
      "19,43": 3,
      "19,44": 2,
      "19,45": 2,
      "19,46": 2,
      "19,47": 2,
      "19,48": 2,
      "20,0": 0,
      "20,3": 15,
      "20,4": 15,
      "20,5": 15,
      "20,6": 15,
      "20,7": 15,
      "20,8": 15,
      "20,9": 15,
      "20,10": 15,
      "20,11": 15,
      "20,12": 15,
      "20,13": 15,
      "20,14": 15,
      "20,15": 15,
      "20,16": 15,
      "20,17": 15,
      "20,43": 2,
      "20,44": 2,
      "20,45": 2,
      "20,46": 2,
      "20,47": 2,
      "20,48": 2,
      "20,52": 2,
      "21,0": 0,
      "21,3": 15,
      "21,4": 15,
      "21,5": 15,
      "21,6": 15,
      "21,7": 15,
      "21,8": 15,
      "21,9": 15,
      "21,10": 15,
      "21,11": 15,
      "21,12": 15,
      "21,13": 15,
      "21,14": 15,
      "21,15": 15,
      "21,16": 15,
      "21,17": 15,
      "21,20": 16,
      "21,21": 2,
      "21,22": 2,
      "21,23": 2,
      "21,24": 2,
      "21,25": 2,
      "21,26": 2,
      "21,27": 16,
      "21,28": 2,
      "21,29": 2,
      "21,30": 2,
      "21,31": 2,
      "21,35": 2,
      "21,36": 2,
      "21,37": 2,
      "21,43": 1,
      "21,44": 2,
      "21,45": 2,
      "21,46": 2,
      "21,47": 2,
      "21,48": 2,
      "21,52": 2,
      "22,0": 0,
      "22,35": 17,
      "22,36": 2,
      "22,37": 2,
      "22,43": 3,
      "22,44": 2,
      "22,45": 2,
      "22,46": 2,
      "22,47": 2,
      "22,48": 2,
      "22,49": 2,
      "22,50": 2,
      "22,51": 2,
      "22,52": 2,
      "23,0": 0,
      "23,43": 2,
      "23,44": 2,
      "23,45": 2,
      "23,46": 2,
      "23,47": 2,
      "23,48": 2,
      "23,52": 2,
      "24,0": 0,
      "24,43": 1,
      "24,44": 2,
      "24,45": 2,
      "24,46": 2,
      "24,47": 2,
      "24,48": 2,
      "24,52": 2,
      "25,0": 0,
      "25,43": 3,
      "25,44": 2,
      "25,45": 2,
      "25,46": 2,
      "25,47": 2,
      "25,48": 2,
      "25,52": 2,
      "26,0": 0,
      "26,43": 2,
      "26,44": 2,
      "26,45": 2,
      "26,46": 2,
      "26,47": 2,
      "26,48": 2,
      "26,52": 2,
      "27,0": 0,
      "27,43": 1,
      "27,44": 2,
      "27,45": 2,
      "27,46": 2,
      "27,47": 2,
      "27,48": 2,
      "27,52": 2,
      "28,0": 0,
      "28,35": 2,
      "28,36": 2,
      "28,37": 2,
      "28,43": 3,
      "28,44": 2,
      "28,45": 2,
      "29,0": 0,
      "29,43": 2,
      "29,44": 2,
      "29,45": 2,
      "30,0": 0,
      "30,43": 1,
      "30,44": 2,
      "30,45": 2,
      "31,0": 0,
      "31,32": 2,
      "31,33": 2,
      "31,37": 2,
      "31,38": 2,
      "31,39": 2,
      "31,40": 2,
      "31,41": 2,
      "31,42": 2,
      "31,43": 18,
      "31,44": 2,
      "31,45": 2,
      "31,46": 2,
      "31,47": 2,
      "31,48": 2,
      "31,49": 2,
      "31,50": 2,
      "31,51": 2,
      "31,52": 2,
      "32,32": 2,
      "32,33": 2,
      "32,37": 2,
      "32,38": 2,
      "32,39": 2,
      "32,40": 2,
      "32,41": 2,
      "32,42": 2,
      "32,43": 2,
      "32,44": 2,
      "32,45": 2,
      "32,46": 2,
      "32,47": 2,
      "32,48": 2,
      "32,49": 2,
      "32,50": 2,
      "32,51": 2,
      "32,52": 2,
      "33,32": 2,
      "33,33": 2,
      "33,37": 2,
      "33,38": 2,
      "33,39": 2,
      "33,40": 2,
      "33,41": 2,
      "33,42": 2,
      "33,43": 2,
      "33,44": 2,
      "33,45": 2,
      "33,46": 2,
      "33,47": 2,
      "33,48": 2,
      "33,49": 2,
      "33,50": 2,
      "33,51": 2,
      "33,52": 2
    },
    "SheetStyle": {
      "FontFamily": 1
    }
  },
  "Spans": [
    "2,3,8,29",
    "4,35,1,3",
    "16,24,1,8",
    "10,35,1,3",
    "1,35,1,3",
    "12,24,1,7",
    "21,20,1,6",
    "21,27,1,5",
    "19,3,1,19",
    "7,35,1,3",
    "10,43,1,3",
    "22,35,1,3",
    "12,8,1,6",
    "16,3,1,10",
    "7,43,1,3",
    "1,43,1,3",
    "4,43,1,3",
    "13,35,1,3",
    "19,35,1,3",
    "16,35,1,3",
    "13,43,1,3",
    "31,43,1,3",
    "25,43,1,3",
    "22,43,1,3",
    "28,43,1,3",
    "16,43,1,3",
    "19,43,1,3"
  ],
  "PageInfo": {
    "$type": "Forguncy.Model.Pages.NormalPage, ServerDesignerCommon",
    "ShouldCheckDirty": true,
    "IgnoreDirtyCells": [
      {
        "Value": {
          "$type": "Forguncy.Model.FormulaReferObject, ServerDesignerCommon",
          "SerializeProperty": "=タスク登録編集!編集許可フラグ"
        }
      }
    ],
    "PageLoadedCommandList": [
      {
        "$type": "Forguncy.Model.ConditionCommand, ServerDesignerCommon",
        "ConditionAndCommandPairList": [
          {
            "Condition": {
              "$type": "Forguncy.Model.IfCondition, ServerDesignerCommon",
              "param": {
                "$type": "Forguncy.Model.IfConditionPageElementParam, ServerDesignerCommon",
                "cellLocations": [
                  {
                    "SerializeProperty": "=タスク登録編集!AJ5"
                  }
                ]
              },
              "value": "%Null%"
            },
            "CommandList": [
              {
                "$type": "Forguncy.Model.SetCellPropertyCommand, ServerDesignerCommon",
                "PropertyItemsList": [
                  {
                    "TargetCells": {
                      "$type": "Forguncy.Model.FormulaReferObject, ServerDesignerCommon",
                      "SerializeProperty": "=タスク登録編集!AB22"
                    },
                    "Value": "登録する"
                  }
                ]
              }
            ],
            "ID": "371066ef-22d5-4f9d-9f36-8cea12836cbb"
          },
          {
            "CommandList": [
              {
                "$type": "Forguncy.Model.SetCellPropertyCommand, ServerDesignerCommon",
                "PropertyItemsList": [
                  {
                    "TargetCells": {
                      "$type": "Forguncy.Model.FormulaReferObject, ServerDesignerCommon",
                      "SerializeProperty": "=タスク登録編集!AB22"
                    },
                    "Value": "更新する"
                  }
                ]
              },
              {
                "$type": "Forguncy.Model.ShareCommand, ServerDesignerCommon",
                "ShareCommandContainerRefer": {
                  "ShareCommandContainerID": "4f87d22b-cc0e-415b-8d3e-230f5aaece5d"
                },
                "Params": [
                  {
                    "ParamReferObject": {
                      "ParamID": "47e4abdf-02d9-4089-a30b-e2047e8afcf5",
                      "ShareCommandContainerReferObject": {
                        "ShareCommandContainerID": "4f87d22b-cc0e-415b-8d3e-230f5aaece5d"
                      }
                    },
                    "Value": {
                      "$type": "Forguncy.Model.FormulaReferObject, ServerDesignerCommon",
                      "SerializeProperty": "=タスク登録編集!AJ17"
                    }
                  },
                  {
                    "ParamReferObject": {
                      "ParamID": "3d985501-ddd4-40b7-8aed-2543a20606d3",
                      "ShareCommandContainerReferObject": {
                        "ShareCommandContainerID": "4f87d22b-cc0e-415b-8d3e-230f5aaece5d"
                      }
                    }
                  }
                ],
                "ReturnPropertiesTo": [
                  {
                    "ReturnPropertyReferObject": {
                      "ParamID": "55afc03c-8864-40e6-ace6-c4af0cb45500",
                      "ShareCommandContainerReferObject": {
                        "ShareCommandContainerID": "4f87d22b-cc0e-415b-8d3e-230f5aaece5d"
                      }
                    },
                    "ResultTo": {
                      "SerializeProperty": "=タスク登録編集!編集許可フラグ"
                    }
                  }
                ]
              }
            ],
            "ID": "4292ba3f-4511-4b45-97bc-5fe94ccb6030"
          }
        ]
      }
    ],
    "AuthorizeInfo": {
      "VisitMode": 2
    },
    "RowBreakLines": [],
    "RepeatRangeSettings": [],
    "RelatedDataTableName": "t_task",
    "PageResponsiveMode": 2
  },
  "PrintInfo": {
    "Margin": {},
    "PaperSize": {}
  },
  "CustomNames": [
    {
      "Name": "タブID",
      "Formula": "タスク登録編集!$AQ$2"
    },
    {
      "Name": "更新フラグ",
      "Formula": "タスク登録編集!$AR$2"
    },
    {
      "Name": "編集許可フラグ",
      "Formula": "タスク登録編集!$AR$5"
    }
  ]
}//QKsH0SSqD9DzaowV/ouv4ClAp/8WjpklmgUDQzhoyhP1S5J7DPfKYiKOiT0f9XSQ5hjFBVnfpZckwu8KKu5hcEPhh+wiIX+dkQoFPXcBrMcmykj2hyZ3ZYaS+a/IufegOthsZY7EWKI3TtQQCK3Q4UUcQ0QQee3acY4+nfTGNoMHQygMMtFDQ03ExTghh0jdQ1lNXNvDlBLfGd8C044I11jK+5B5uhCteN7C653/F6aJasbIkEgaFBCn2tWp3J477MRCU9S6ZsR6SZG6zl6ckJldUp7IZUAYLqfcyFDOfD8D4WVWd8byaXM2RWzz8gRz17X/mO61w+0IxjwmkYsmegJRu62mm4HnsFOiPpPoPA7z6lfcm4qxKOO+X9tJy9mhZdk8rs8GBeLpcIl04NCR8Tf+lkLY/Tglr3zYjJyG+bpHjaFBKFXkfiiA43qsZp0OoDVA/yxZUISSFVtA9BUfcP+gYa6XWZWJTkffd9f8aQR/Gle0JtV/LE7hEbDYqne+tHlk5xa3TiYrmxvxRb1lYotK1lm7UK2KrNj2m6xe/42pcGkesg1hH1Kj/Sm7KyuLxKTJQAySTTIV0eMsWIWcxBO0feUNTi2UFZXpgs9wYXsd7sCChiiV40FNkpkurJtFHlEQmeMJebtmFXbWomhxxzk76/+jCtdU6JZkJo441jlMHeb1H9LtY6fRatIqKm0mbKNattsq5gmQyFBlEl3ie0aSH9IhBgU6BDw1+cVZcNOYJEET8h8frYpeEDyuq4W+X2bmFkKJ6hBcpwCyJn4IDXUSXnQ3o5Dv3+g899oBwhtbuSMSgLt9jt0G2XS9JTescIpA39wuQy2gtxo0LfoH14lyP0f4uybItDu+g2aUwsnnEchjYkEYSUNXgbBmj86NCBTHy+55q3WkCr9ZTu7pVg==|920